odoo/addons/purchase_sale_stock_inter_company_mrp/README.rst
odoo/addons/purchase_sale_stock_inter_company_mrp/__init__.py
odoo/addons/purchase_sale_stock_inter_company_mrp/__manifest__.py
odoo/addons/purchase_sale_stock_inter_company_mrp/i18n/it.po
odoo/addons/purchase_sale_stock_inter_company_mrp/i18n/purchase_sale_stock_inter_company_mrp.pot
odoo/addons/purchase_sale_stock_inter_company_mrp/models/__init__.py
odoo/addons/purchase_sale_stock_inter_company_mrp/models/stock_picking.py
odoo/addons/purchase_sale_stock_inter_company_mrp/readme/CONTRIBUTORS.rst
odoo/addons/purchase_sale_stock_inter_company_mrp/readme/DESCRIPTION.rst
odoo/addons/purchase_sale_stock_inter_company_mrp/static/description/icon.png
odoo/addons/purchase_sale_stock_inter_company_mrp/static/description/index.html
odoo/addons/purchase_sale_stock_inter_company_mrp/tests/__init__.py
odoo/addons/purchase_sale_stock_inter_company_mrp/tests/test_inter_company_purchase_sale_stock_mrp.py
odoo_addon_purchase_sale_stock_inter_company_mrp-16.0.1.0.0.4.dist-info/METADATA
odoo_addon_purchase_sale_stock_inter_company_mrp-16.0.1.0.0.4.dist-info/WHEEL
odoo_addon_purchase_sale_stock_inter_company_mrp-16.0.1.0.0.4.dist-info/top_level.txt
odoo_addon_purchase_sale_stock_inter_company_mrp-16.0.1.0.0.4.dist-info/RECORD
