Metadata-Version: 2.1
Name: odoo-addon-purchase_sale_stock_inter_company_mrp
Version: 16.0.1.0.0.4
Summary: Intercompany PO/SO rules with MRP
Home-page: https://github.com/OCA/multi-company
Author: ForgeFlow, Odoo Community Association (OCA)
Author-email: support@odoo-community.org
License: AGPL-3
Classifier: Programming Language :: Python
Classifier: Framework :: Odoo
Classifier: Framework :: Odoo :: 16.0
Classifier: License :: OSI Approved :: GNU Affero General Public License v3
Requires-Python: >=3.10
Requires-Dist: odoo-addon-purchase-sale-stock-inter-company<16.1dev,>=16.0dev
Requires-Dist: odoo<16.1dev,>=16.0a
